snail/__init__.py
snail/__main__.py
snail/cli.py
snail/core/__init__.py
snail/core/intersections.cp312-win_amd64.pyd
snail/damages.py
snail/intersection.py
snail/io.py
snail/routing.py
snail/tqdm_standin.py
nismod_snail-0.5.4.dist-info/METADATA
nismod_snail-0.5.4.dist-info/WHEEL
nismod_snail-0.5.4.dist-info/entry_points.txt
nismod_snail-0.5.4.dist-info/licenses/LICENSE
nismod_snail-0.5.4.dist-info/RECORD
