Metadata-Version: 2.1
Name: nismod-snail
Version: 0.5.4
Summary: The spatial networks impact assessment library
Author: Thibault Lestang, Raghav Pant, Lena Fuldauer
Author-Email: Tom Russell <tomalrussell@gmail.com>
Maintainer-Email: Tom Russell <tomalrussell@gmail.com>
License: MIT License
Classifier: Development Status :: 4 - Beta
Classifier: Intended Audience :: Science/Research
Classifier: License :: OSI Approved :: MIT License
Classifier: Programming Language :: Python
Classifier: Programming Language :: Python :: 3
Classifier: Topic :: Scientific/Engineering :: GIS
Classifier: Topic :: Utilities
Project-URL: Homepage, https://github.com/nismod/snail
Project-URL: Documentation, https://nismod.github.io/snail/
Project-URL: Repository, https://github.com/nismod/snail.git
Requires-Python: >=3.8
Requires-Dist: geopandas
Requires-Dist: matplotlib
Requires-Dist: numpy
Requires-Dist: openpyxl
Requires-Dist: pandera
Requires-Dist: pyarrow
Requires-Dist: pyogrio
Requires-Dist: igraph
Requires-Dist: rasterio
Requires-Dist: shapely
Requires-Dist: scipy
Requires-Dist: affine; extra == "dev"
Requires-Dist: black; extra == "dev"
Requires-Dist: hilbertcurve; extra == "dev"
Requires-Dist: nbstripout; extra == "dev"
Requires-Dist: pytest-cov; extra == "dev"
Requires-Dist: pytest; extra == "dev"
Requires-Dist: sphinx; extra == "docs"
Requires-Dist: nbsphinx; extra == "docs"
Requires-Dist: sphinx_gallery; extra == "docs"
Requires-Dist: numpydoc; extra == "docs"
Requires-Dist: contextily; extra == "tutorials"
Requires-Dist: irv_autopkg_client; extra == "tutorials"
Requires-Dist: jupyter; extra == "tutorials"
Requires-Dist: networkx; extra == "tutorials"
Requires-Dist: seaborn; extra == "tutorials"
Requires-Dist: snkit; extra == "tutorials"
Requires-Dist: tqdm; extra == "tutorials"
Provides-Extra: dev
Provides-Extra: docs
Provides-Extra: tutorials
